odoo/addons/disable_login/__init__.py
odoo/addons/disable_login/__manifest__.py
odoo/addons/disable_login/controllers/__init__.py
odoo/addons/disable_login/controllers/main.py
odoo/addons/disable_login/views/auth_templates.xml
odoo12_addon_disable_login-12.0.1.1.1.dist-info/METADATA
odoo12_addon_disable_login-12.0.1.1.1.dist-info/WHEEL
odoo12_addon_disable_login-12.0.1.1.1.dist-info/top_level.txt
odoo12_addon_disable_login-12.0.1.1.1.dist-info/RECORD
